Metadata-Version: 2.4
Name: hutb_doc
Version: 1.5.6
Summary: Project documentation with Markdown.
Project-URL: Documentation, https://www.mkdocs.org/
Project-URL: Source, https://github.com/mkdocs/mkdocs
Project-URL: Issues, https://github.com/mkdocs/mkdocs/issues
Project-URL: History, https://www.mkdocs.org/about/release-notes/
Author-email: Tom Christie <tom@tomchristie.com>
License-Expression: BSD-2-Clause
License-File: LICENSE
Classifier: Development Status :: 5 - Production/Stable
Classifier: Environment :: Console
Classifier: Environment :: Web Environment
Classifier: Intended Audience :: Developers
Classifier: License :: OSI Approved :: BSD License
Classifier: Operating System :: OS Independent
Classifier: Programming Language :: Python
Classifier: Programming Language :: Python :: 3
Classifier: Programming Language :: Python :: 3 :: Only
Classifier: Programming Language :: Python :: 3.8
Classifier: Programming Language :: Python :: 3.9
Classifier: Programming Language :: Python :: 3.10
Classifier: Programming Language :: Python :: 3.11
Classifier: Programming Language :: Python :: 3.12
Classifier: Programming Language :: Python :: Implementation :: CPython
Classifier: Programming Language :: Python :: Implementation :: PyPy
Classifier: Topic :: Documentation
Classifier: Topic :: Text Processing
Requires-Python: >=3.8
Requires-Dist: click>=7.0
Requires-Dist: colorama>=0.4; platform_system == 'Windows'
Requires-Dist: ghp-import>=1.0
Requires-Dist: importlib-metadata>=4.4; python_version < '3.10'
Requires-Dist: jinja2>=2.11.1
Requires-Dist: markdown>=3.3.6
Requires-Dist: markupsafe>=2.0.1
Requires-Dist: mergedeep>=1.3.4
Requires-Dist: mkdocs-get-deps>=0.2.0
Requires-Dist: packaging>=20.5
Requires-Dist: pathspec>=0.11.1
Requires-Dist: pyyaml-env-tag>=0.1
Requires-Dist: pyyaml>=5.1
Requires-Dist: watchdog>=2.0
Provides-Extra: i18n
Requires-Dist: babel>=2.9.0; extra == 'i18n'
Requires-Dist: setuptools; (python_version >= '3.12') and extra == 'i18n'
Provides-Extra: min-versions
Requires-Dist: babel==2.9.0; extra == 'min-versions'
Requires-Dist: click==7.0; extra == 'min-versions'
Requires-Dist: colorama==0.4; (platform_system == 'Windows') and extra == 'min-versions'
Requires-Dist: ghp-import==1.0; extra == 'min-versions'
Requires-Dist: importlib-metadata==4.4; (python_version < '3.10') and extra == 'min-versions'
Requires-Dist: jinja2==2.11.1; extra == 'min-versions'
Requires-Dist: markdown==3.3.6; extra == 'min-versions'
Requires-Dist: markupsafe==2.0.1; extra == 'min-versions'
Requires-Dist: mergedeep==1.3.4; extra == 'min-versions'
Requires-Dist: mkdocs-get-deps==0.2.0; extra == 'min-versions'
Requires-Dist: packaging==20.5; extra == 'min-versions'
Requires-Dist: pathspec==0.11.1; extra == 'min-versions'
Requires-Dist: pyyaml-env-tag==0.1; extra == 'min-versions'
Requires-Dist: pyyaml==5.1; extra == 'min-versions'
Requires-Dist: watchdog==2.0; extra == 'min-versions'
